takproto/__init__.py
takproto/constants.py
takproto/delimited_protobuf.py
takproto/functions.py
takproto/proto/__init__.py
takproto/proto/contact_pb2.py
takproto/proto/cotevent_pb2.py
takproto/proto/detail_pb2.py
takproto/proto/group_pb2.py
takproto/proto/precisionlocation_pb2.py
takproto/proto/status_pb2.py
takproto/proto/takcontrol_pb2.py
takproto/proto/takmessage_pb2.py
takproto/proto/takv_pb2.py
takproto/proto/track_pb2.py
takproto-3.0.0.dist-info/LICENSE
takproto-3.0.0.dist-info/METADATA
takproto-3.0.0.dist-info/WHEEL
takproto-3.0.0.dist-info/top_level.txt
takproto-3.0.0.dist-info/RECORD
