Metadata-Version: 2.1
Name: takproto
Version: 3.0.0
Summary: TAKProto is a Python package to encode and decode TAK data.
Home-page: https://github.com/snstac/takproto
Maintainer: Greg Albrecht <oss@undef.net>
Maintainer-email: oss@undef.net
License: MIT License
Project-URL: CI: GitHub Actions, https://github.com/snstac/takproto/actions
Project-URL: GitHub: issues, https://github.com/snstac/takproto/issues
Project-URL: GitHub: repo, https://github.com/snstac/takproto
Keywords: Cursor on Target,CoT,ATAK,TAK,WinTAK,iTAK,TAK Server,TAKX,Protobuf
Classifier: License :: OSI Approved :: MIT License
Classifier: Intended Audience :: Developers
Classifier: Programming Language :: Python
Classifier: Programming Language :: Python :: 3
Classifier: Programming Language :: Python :: 3 :: Only
Classifier: Programming Language :: Python :: 3.6
Classifier: Programming Language :: Python :: 3.7
Classifier: Programming Language :: Python :: 3.8
Classifier: Programming Language :: Python :: 3.9
Classifier: Programming Language :: Python :: 3.10
Classifier: Programming Language :: Python :: 3.11
Classifier: Programming Language :: Python :: 3.12
Classifier: Development Status :: 5 - Production/Stable
Classifier: Operating System :: POSIX
Classifier: Operating System :: MacOS :: MacOS X
Classifier: Operating System :: Microsoft :: Windows
Classifier: Operating System :: OS Independent
Requires-Python: <4,>=3.6
License-File: LICENSE
Requires-Dist: protobuf >=4.21.0
Provides-Extra: test
Requires-Dist: pytest-cov ; extra == 'test'
Requires-Dist: pylint ; extra == 'test'
Requires-Dist: flake8 ; extra == 'test'
Requires-Dist: black ; extra == 'test'
